MANIFEST.in
README.md
setup.py
netblocks/LICENSE
netblocks/README.md
netblocks/__init__.py
netblocks/netblocks.py
netblocks.egg-info/PKG-INFO
netblocks.egg-info/SOURCES.txt
netblocks.egg-info/dependency_links.txt
netblocks.egg-info/requires.txt
netblocks.egg-info/top_level.txt