Metadata-Version: 2.1
Name: netblocks
Version: 0.0.6
Summary: Get the Google netblocks
Home-page: https://github.com/hm-distro/netblocks/
Author: hm-distro
License: Apache 2
Platform: any
Classifier: Programming Language :: Python :: 2
Classifier: License :: OSI Approved :: Apache Software License
Classifier: Operating System :: OS Independent
